valer.jsonapi-1.2.3rc11-nspkg.pth
senaite/jsonapi/__init__.py
senaite/jsonapi/api.py
senaite/jsonapi/batch.py
senaite/jsonapi/catalog.py
senaite/jsonapi/config.py
senaite/jsonapi/configure.zcml
senaite/jsonapi/datamanagers.py
senaite/jsonapi/dataproviders.py
senaite/jsonapi/exceptions.py
senaite/jsonapi/fieldmanagers.py
senaite/jsonapi/interfaces.py
senaite/jsonapi/request.py
senaite/jsonapi/underscore.py
senaite/jsonapi/tests/__init__.py
senaite/jsonapi/tests/base.py
senaite/jsonapi/tests/test_doctests.py
senaite/jsonapi/tests/test_setup.py
senaite/jsonapi/v1/__init__.py
senaite/jsonapi/v1/configure.zcml
senaite/jsonapi/v1/routes/__init__.py
senaite/jsonapi/v1/routes/catalogs.py
senaite/jsonapi/v1/routes/content.py
senaite/jsonapi/v1/routes/push.py
senaite/jsonapi/v1/routes/registry.py
senaite/jsonapi/v1/routes/settings.py
senaite/jsonapi/v1/routes/users.py
senaite/jsonapi/v1/routes/version.py
valer.jsonapi-1.2.3rc11.dist-info/DESCRIPTION.rst
valer.jsonapi-1.2.3rc11.dist-info/METADATA
valer.jsonapi-1.2.3rc11.dist-info/RECORD
valer.jsonapi-1.2.3rc11.dist-info/WHEEL
valer.jsonapi-1.2.3rc11.dist-info/entry_points.txt
valer.jsonapi-1.2.3rc11.dist-info/metadata.json
valer.jsonapi-1.2.3rc11.dist-info/namespace_packages.txt
valer.jsonapi-1.2.3rc11.dist-info/top_level.txt
